[
	{
		"name": "三台",
		"abc": "ㄙㄊ"
	},
	{
		"name": "大莊路",
		"abc": "ㄉㄓㄌ"
	},
	{
		"name": "中山路",
		"abc": "ㄓㄕㄌ"
	},
	{
		"name": "中興路",
		"abc": "ㄓㄒㄌ"
	},
	{
		"name": "六十石山",
		"abc": "ㄌㄕㄕㄕ"
	},
	{
		"name": "公界街",
		"abc": "ㄍㄐㄐ"
	},
	{
		"name": "公埔路",
		"abc": "ㄍㄆㄌ"
	},
	{
		"name": "公埔路２段",
		"abc": "ㄍㄆㄌㄉ"
	},
	{
		"name": "文化路",
		"abc": "ㄨㄏㄌ"
	},
	{
		"name": "四維",
		"abc": "ㄙㄨ"
	},
	{
		"name": "民權路",
		"abc": "ㄇㄑㄌ"
	},
	{
		"name": "永安街",
		"abc": "ㄩㄢㄐ"
	},
	{
		"name": "永豐",
		"abc": "ㄩㄈ"
	},
	{
		"name": "永豐村復興",
		"abc": "ㄩㄈㄘㄈㄒ"
	},
	{
		"name": "石牌",
		"abc": "ㄕㄆ"
	},
	{
		"name": "光明路",
		"abc": "ㄍㄇㄌ"
	},
	{
		"name": "后庄路",
		"abc": "ㄏㄌ"
	},
	{
		"name": "安通",
		"abc": "ㄢㄊ"
	},
	{
		"name": "安靜街",
		"abc": "ㄢㄐㄐ"
	},
	{
		"name": "吳江",
		"abc": "ㄨㄐ"
	},
	{
		"name": "車站街",
		"abc": "ㄔㄓㄐ"
	},
	{
		"name": "車站街１段",
		"abc": "ㄔㄓㄐㄉ"
	},
	{
		"name": "和平街",
		"abc": "ㄏㄆㄐ"
	},
	{
		"name": "明里",
		"abc": "ㄇㄌ"
	},
	{
		"name": "東竹",
		"abc": "ㄉㄓ"
	},
	{
		"name": "東里村復興",
		"abc": "ㄉㄌㄘㄈㄒ"
	},
	{
		"name": "東昇路",
		"abc": "ㄉㄕㄌ"
	},
	{
		"name": "東湖",
		"abc": "ㄉㄏ"
	},
	{
		"name": "東寧",
		"abc": "ㄉㄋ"
	},
	{
		"name": "東興",
		"abc": "ㄉㄒ"
	},
	{
		"name": "南興路",
		"abc": "ㄋㄒㄌ"
	},
	{
		"name": "草坪",
		"abc": "ㄘㄆ"
	},
	{
		"name": "清坑",
		"abc": "ㄑㄎ"
	},
	{
		"name": "富北",
		"abc": "ㄈㄅ"
	},
	{
		"name": "富田",
		"abc": "ㄈㄊ"
	},
	{
		"name": "富南",
		"abc": "ㄈㄋ"
	},
	{
		"name": "富豐路",
		"abc": "ㄈㄈㄌ"
	},
	{
		"name": "復興路",
		"abc": "ㄈㄒㄌ"
	},
	{
		"name": "朝寧",
		"abc": "ㄔㄋ"
	},
	{
		"name": "湧泉路",
		"abc": "ㄩㄑㄌ"
	},
	{
		"name": "雲閩",
		"abc": "ㄩㄇ"
	},
	{
		"name": "新莊",
		"abc": "ㄒㄓ"
	},
	{
		"name": "新富",
		"abc": "ㄒㄈ"
	},
	{
		"name": "新興",
		"abc": "ㄒㄒ"
	},
	{
		"name": "源和",
		"abc": "ㄩㄏ"
	},
	{
		"name": "萬寧",
		"abc": "ㄨㄋ"
	},
	{
		"name": "道化路",
		"abc": "ㄉㄏㄌ"
	},
	{
		"name": "福安路",
		"abc": "ㄈㄢㄌ"
	},
	{
		"name": "福崗",
		"abc": "ㄈㄍ"
	},
	{
		"name": "廣興路",
		"abc": "ㄍㄒㄌ"
	},
	{
		"name": "慶光路",
		"abc": "ㄑㄍㄌ"
	},
	{
		"name": "學富路",
		"abc": "ㄒㄈㄌ"
	},
	{
		"name": "豐南",
		"abc": "ㄈㄋ"
	},
	{
		"name": "豐南村復興",
		"abc": "ㄈㄋㄘㄈㄒ"
	},
	{
		"name": "鎮寧",
		"abc": "ㄓㄋ"
	},
	{
		"name": "羅山",
		"abc": "ㄌㄕ"
	}
]