[
	{
		"name": "二十分",
		"abc": "ㄦㄕㄈ"
	},
	{
		"name": "二本松",
		"abc": "ㄦㄅㄙ"
	},
	{
		"name": "八卦力",
		"abc": "ㄅㄍㄌ"
	},
	{
		"name": "大安",
		"abc": "ㄉㄢ"
	},
	{
		"name": "小南角",
		"abc": "ㄒㄋㄐ"
	},
	{
		"name": "天狗",
		"abc": "ㄊㄍ"
	},
	{
		"name": "半天寮",
		"abc": "ㄅㄊㄌ"
	},
	{
		"name": "司馬限",
		"abc": "ㄙㄇㄒ"
	},
	{
		"name": "永安",
		"abc": "ㄩㄢ"
	},
	{
		"name": "長橋",
		"abc": "ㄔㄑ"
	},
	{
		"name": "南灣",
		"abc": "ㄋㄨ"
	},
	{
		"name": "洗水坑",
		"abc": "ㄒㄕㄎ"
	},
	{
		"name": "馬那邦",
		"abc": "ㄇㄋㄅ"
	},
	{
		"name": "高熊𡶛",
		"abc": "ㄍㄒundefined"
	},
	{
		"name": "梅園",
		"abc": "ㄇㄩ"
	},
	{
		"name": "象鼻",
		"abc": "ㄒㄅ"
	},
	{
		"name": "圓墩",
		"abc": "ㄩㄉ"
	},
	{
		"name": "腦寮庄",
		"abc": "ㄋㄌundefined"
	},
	{
		"name": "橫龍山",
		"abc": "ㄏㄌㄕ"
	},
	{
		"name": "蘇魯",
		"abc": "ㄙㄌ"
	}
]